<StructureDefinition xmlns="http://hl7.org/fhir">
  <id value="chmed16af-simplequantity"/>
  <url value="http://chmed16af.emediplan.ch/fhir/StructureDefinition/chmed16af-simplequantity"/>
  <version value="0.1.0"/>
  <name value="QuantityCDTYP9UnitCodes"/>
  <title value="Quantity with CDTYP 9 UnitCodes"/>
  <status value="draft"/>
  <publisher value="IG eMediplan"/>
  <contact>
    <telecom>
      <system value="url"/>
      <value value="http://www.emediplan.ch"/>
    </telecom>
  </contact>
  <description value="A prescription can be structured in a bundle according to the prescription bundle profile."/>
  <fhirVersion value="4.0.1"/>
  <mapping>
    <identity value="CHMED16A"/>
    <uri value="http://emediplan.ch/chmed16a"/>
    <name value="Mapping to CHMED16A"/>
  </mapping>
  <kind value="complex-type"/>
  <abstract value="false"/>
  <type value="Quantity"/>
  <baseDefinition value="http://hl7.org/fhir/StructureDefinition/SimpleQuantity"/>
  <derivation value="constraint"/>
  <differential>
    <element id="Quantity">
      <path value="Quantity"/>
      <short value="A fixed quantity (no comparator)"/>
      <definition value="The comparator is not used on a SimpleQuantity"/>
      <min value="0"/>
      <max value="*"/>
    </element>
    <element id="Quantity.system">
      <path value="Quantity.system" />
      <min value="1" />
      <max value="1" />
      <type>
        <code value="uri" />
      </type>
      <fixedUri value="http://chmed16af.emediplan.ch/fhir/CodeSystem/chmed16af-codesystem-cdtyp9" />
    </element>
  </differential>
</StructureDefinition>